{
  "mode": "paper",
  "brokerMode": "paper",
  "paperTradingOnly": true,
  "liveTradingEnabled": false,
  "autoTradingEnabled": true,
  "autoExecuteApprovedSignals": true,
  "maxTradeAmount": 10000,
  "maxDailyLoss": 200,
  "dailyProfitTarget": 500,
  "maxTradesPerDay": 100,
  "aiStrategyEnabled": true,
  "strategyProfile": "conservative_trend",
  "tradeDirection": "long_only",
  "entryStrategy": "pullback_to_vwap",
  "exitStrategy": "bracket_target_stop",
  "maxHoldMinutes": 120,
  "maxSignalAgeMinutes": 5,
  "minRewardRiskRatio": 1.6,
  "plannedTradesToday": 1,
  "tradingDirective": "OBSERVE",
  "emergencyStopEnabled": false,
  "emergencyStopReason": null,
  "emergencyStoppedAt": null,
  "maxPositionAmountToday": 0,
  "dailyRiskBudget": 0,
  "lastStrategyDecision": {
    "strategyProfile": "conservative_trend",
    "tradeDirection": "long_only",
    "entryStrategy": "pullback_to_vwap",
    "exitStrategy": "bracket_target_stop",
    "maxHoldMinutes": 120,
    "minRewardRiskRatio": 1.6,
    "confidenceThreshold": 84,
    "plannedTradesToday": 1,
    "tradingDirective": "OBSERVE",
    "maxPositionAmountToday": 0,
    "dailyRiskBudget": 0,
    "reason": "Evidence remains insufficient for automated intraday execution under a conservative, audit-focused long-only mandate: marketCondition is neutral, average RVOL is only modest (1.18) and average gap is moderate (2.36%), while averageLiquidityScore is middling (39.43) and averageCatalystScore is weak (28.85). With only 50% of candidates in uptrends, the probability of clean trend continuation and VWAP-supported pullbacks is reduced and slippage/false-move risk is elevated. Maintain conservative_trend with pullback-to-VWAP and bracketed exits, but allocate no risk and place no new orders today; continue scanning for higher-liquidity, higher-RVOL names with clearer uptrends and VWAP support before enabling trades.",
    "selectedAt": "2026-05-27T13:15:07.907Z",
    "selectedBy": "ai_strategy_agent"
  },
  "confidenceThreshold": 84,
  "minTradeQualityScore": 60,
  "maxConsecutiveLossesBeforePause": 2,
  "lossCooldownMinutes": 30,
  "priceAdjustmentTolerancePercent": 0.25,
  "entrySlippageTolerancePercent": 0.15,
  "partialProfitEnabled": true,
  "partialProfitPercent": 50,
  "partialProfitTriggerPercent": 0.75,
  "trailingStopEnabled": true,
  "trailingStopPercent": 0.6,
  "trailingStopActivationPercent": 0.9,
  "reentryEnabled": true,
  "maxReentriesPerSymbol": 1,
  "scannerMinPrice": 5,
  "scannerMaxPrice": 1000,
  "scannerMinRelativeVolume": 1,
  "scannerMaxCandidates": 20,
  "preferredSymbols": [],
  "excludedSymbols": [],
  "updatedAt": "2026-05-27T13:15:08.090Z",
  "availableModes": {
    "paper": true,
    "live": true
  }
}